container_inspector/__init__.py
container_inspector/cli.py
container_inspector/distro.py
container_inspector/dockerfile.py
container_inspector/image.py
container_inspector/rootfs.py
container_inspector/utils.py
container_inspector-33.1.0.dist-info/licenses/AUTHORS.rst
container_inspector-33.1.0.dist-info/licenses/CHANGELOG.rst
container_inspector-33.1.0.dist-info/licenses/CODE_OF_CONDUCT.rst
container_inspector-33.1.0.dist-info/licenses/NOTICE
container_inspector-33.1.0.dist-info/licenses/README.rst
container_inspector-33.1.0.dist-info/licenses/apache-2.0.LICENSE
container_inspector-33.1.0.dist-info/METADATA
container_inspector-33.1.0.dist-info/WHEEL
container_inspector-33.1.0.dist-info/entry_points.txt
container_inspector-33.1.0.dist-info/top_level.txt
container_inspector-33.1.0.dist-info/RECORD
