Metadata-Version: 2.4
Name: container-inspector
Version: 33.1.0
Summary: Docker, containers, rootfs and virtual machine related software composition analysis (SCA) utilities.
Home-page: https://github.com/aboutcode-org/container-inspector
Author: nexB. Inc. and others
Author-email: info@aboutcode.org
License: Apache-2.0
Keywords: utilities,docker,container,oci,qcow,os-release,virtual-machine,vm,rootfs,scancode
Classifier: Development Status :: 5 - Production/Stable
Classifier: Intended Audience :: Developers
Classifier: Operating System :: POSIX
Classifier: Programming Language :: Python :: 3
Classifier: Programming Language :: Python :: 3 :: Only
Classifier: Programming Language :: Python :: 3.10
Classifier: Programming Language :: Python :: 3.11
Classifier: Programming Language :: Python :: 3.12
Classifier: Programming Language :: Python :: 3.13
Classifier: Programming Language :: Python :: 3.14
Classifier: Topic :: Software Development
Classifier: Topic :: Utilities
Requires-Python: >=3.10
License-File: apache-2.0.LICENSE
License-File: NOTICE
License-File: AUTHORS.rst
License-File: CHANGELOG.rst
License-File: CODE_OF_CONDUCT.rst
License-File: README.rst
Requires-Dist: click!=7.0,!=8.0.3,>=6.7
Requires-Dist: attrs!=20.1.0,>=18.1
Requires-Dist: dockerfile_parse
Requires-Dist: commoncode>=31.2.1
Provides-Extra: dev
Requires-Dist: pytest>=7.0.1; extra == "dev"
Requires-Dist: pytest-xdist>=2; extra == "dev"
Requires-Dist: aboutcode-toolkit>=7.0.2; extra == "dev"
Requires-Dist: twine; extra == "dev"
Requires-Dist: ruff; extra == "dev"
Requires-Dist: Sphinx>=5.0.2; extra == "dev"
Requires-Dist: sphinx-rtd-theme>=1.0.0; extra == "dev"
Requires-Dist: sphinx-reredirects>=0.1.2; extra == "dev"
Requires-Dist: doc8>=0.11.2; extra == "dev"
Requires-Dist: sphinx-autobuild; extra == "dev"
Requires-Dist: sphinx-rtd-dark-mode>=1.3.0; extra == "dev"
Requires-Dist: sphinx-copybutton; extra == "dev"
Dynamic: license-file
